plexdl/__init__.py
plexdl/cli.py
plexdl/plexdl.py
plexdl-0.5.0.dist-info/METADATA
plexdl-0.5.0.dist-info/WHEEL
plexdl-0.5.0.dist-info/entry_points.txt
plexdl-0.5.0.dist-info/licenses/LICENSE
plexdl-0.5.0.dist-info/RECORD
